[
    {
        "type": "convention",
        "module": "src.adb_client",
        "obj": "",
        "line": 227,
        "column": 0,
        "endLine": null,
        "endColumn": null,
        "path": "src\\adb_client.py",
        "symbol": "trailing-whitespace",
        "message": "Trailing whitespace",
        "message-id": "C0303"
    },
    {
        "type": "convention",
        "module": "src.adb_client",
        "obj": "",
        "line": 273,
        "column": 0,
        "endLine": null,
        "endColumn": null,
        "path": "src\\adb_client.py",
        "symbol": "trailing-whitespace",
        "message": "Trailing whitespace",
        "message-id": "C0303"
    },
    {
        "type": "convention",
        "module": "src.adb_client",
        "obj": "",
        "line": 278,
        "column": 0,
        "endLine": null,
        "endColumn": null,
        "path": "src\\adb_client.py",
        "symbol": "trailing-whitespace",
        "message": "Trailing whitespace",
        "message-id": "C0303"
    },
    {
        "type": "convention",
        "module": "src.adb_client",
        "obj": "",
        "line": 306,
        "column": 0,
        "endLine": null,
        "endColumn": null,
        "path": "src\\adb_client.py",
        "symbol": "trailing-whitespace",
        "message": "Trailing whitespace",
        "message-id": "C0303"
    },
    {
        "type": "convention",
        "module": "src.adb_client",
        "obj": "",
        "line": 309,
        "column": 0,
        "endLine": null,
        "endColumn": null,
        "path": "src\\adb_client.py",
        "symbol": "trailing-whitespace",
        "message": "Trailing whitespace",
        "message-id": "C0303"
    },
    {
        "type": "convention",
        "module": "src.adb_client",
        "obj": "",
        "line": 343,
        "column": 0,
        "endLine": null,
        "endColumn": null,
        "path": "src\\adb_client.py",
        "symbol": "trailing-whitespace",
        "message": "Trailing whitespace",
        "message-id": "C0303"
    },
    {
        "type": "convention",
        "module": "src.adb_client",
        "obj": "",
        "line": 383,
        "column": 0,
        "endLine": null,
        "endColumn": null,
        "path": "src\\adb_client.py",
        "symbol": "trailing-whitespace",
        "message": "Trailing whitespace",
        "message-id": "C0303"
    },
    {
        "type": "warning",
        "module": "src.adb_client",
        "obj": "ADBClient._run_shell",
        "line": 149,
        "column": 15,
        "endLine": 149,
        "endColumn": 24,
        "path": "src\\adb_client.py",
        "symbol": "broad-exception-caught",
        "message": "Catching too general exception Exception",
        "message-id": "W0718"
    },
    {
        "type": "warning",
        "module": "src.adb_client",
        "obj": "ADBClient._run_shell",
        "line": 141,
        "column": 21,
        "endLine": 147,
        "endColumn": 13,
        "path": "src\\adb_client.py",
        "symbol": "subprocess-run-check",
        "message": "'subprocess.run' used without explicitly defining the value for 'check'.",
        "message-id": "W1510"
    },
    {
        "type": "refactor",
        "module": "src.adb_client",
        "obj": "ADBClient.swipe",
        "line": 198,
        "column": 4,
        "endLine": 198,
        "endColumn": 13,
        "path": "src\\adb_client.py",
        "symbol": "too-many-arguments",
        "message": "Too many arguments (7/5)",
        "message-id": "R0913"
    },
    {
        "type": "warning",
        "module": "src.adb_client",
        "obj": "ADBClient.input_text",
        "line": 286,
        "column": 15,
        "endLine": 286,
        "endColumn": 24,
        "path": "src\\adb_client.py",
        "symbol": "broad-exception-caught",
        "message": "Catching too general exception Exception",
        "message-id": "W0718"
    },
    {
        "type": "warning",
        "module": "src.adb_client",
        "obj": "ADBClient.press_key",
        "line": 322,
        "column": 15,
        "endLine": 322,
        "endColumn": 24,
        "path": "src\\adb_client.py",
        "symbol": "broad-exception-caught",
        "message": "Catching too general exception Exception",
        "message-id": "W0718"
    },
    {
        "type": "warning",
        "module": "src.adb_client",
        "obj": "ADBClient.start_app",
        "line": 363,
        "column": 15,
        "endLine": 363,
        "endColumn": 24,
        "path": "src\\adb_client.py",
        "symbol": "broad-exception-caught",
        "message": "Catching too general exception Exception",
        "message-id": "W0718"
    },
    {
        "type": "warning",
        "module": "src.adb_client",
        "obj": "ADBClient.stop_app",
        "line": 391,
        "column": 15,
        "endLine": 391,
        "endColumn": 24,
        "path": "src\\adb_client.py",
        "symbol": "broad-exception-caught",
        "message": "Catching too general exception Exception",
        "message-id": "W0718"
    },
    {
        "type": "warning",
        "module": "src.adb_client",
        "obj": "ADBClient.list_apps",
        "line": 407,
        "column": 25,
        "endLine": 407,
        "endColumn": 31,
        "path": "src\\adb_client.py",
        "symbol": "unused-variable",
        "message": "Unused variable 'stderr'",
        "message-id": "W0612"
    },
    {
        "type": "warning",
        "module": "src.adb_client",
        "obj": "ADBClient.get_screen_size",
        "line": 455,
        "column": 25,
        "endLine": 455,
        "endColumn": 31,
        "path": "src\\adb_client.py",
        "symbol": "unused-variable",
        "message": "Unused variable 'stderr'",
        "message-id": "W0612"
    },
    {
        "type": "warning",
        "module": "src.adb_client",
        "obj": "ADBClient.get_android_version",
        "line": 478,
        "column": 25,
        "endLine": 478,
        "endColumn": 31,
        "path": "src\\adb_client.py",
        "symbol": "unused-variable",
        "message": "Unused variable 'stderr'",
        "message-id": "W0612"
    },
    {
        "type": "error",
        "module": "src.adb_client",
        "obj": "",
        "line": 504,
        "column": 4,
        "endLine": 504,
        "endColumn": 49,
        "path": "src\\adb_client.py",
        "symbol": "import-error",
        "message": "Unable to import 'device_manager'",
        "message-id": "E0401"
    },
    {
        "type": "warning",
        "module": "src.adb_client",
        "obj": "",
        "line": 7,
        "column": 0,
        "endLine": 7,
        "endColumn": 11,
        "path": "src\\adb_client.py",
        "symbol": "unused-import",
        "message": "Unused import time",
        "message-id": "W0611"
    },
    {
        "type": "warning",
        "module": "src.adb_client",
        "obj": "",
        "line": 9,
        "column": 0,
        "endLine": 9,
        "endColumn": 12,
        "path": "src\\adb_client.py",
        "symbol": "unused-import",
        "message": "Unused import shlex",
        "message-id": "W0611"
    },
    {
        "type": "warning",
        "module": "src.adb_client",
        "obj": "",
        "line": 12,
        "column": 0,
        "endLine": 12,
        "endColumn": 63,
        "path": "src\\adb_client.py",
        "symbol": "unused-import",
        "message": "Unused Device imported from device_manager",
        "message-id": "W0611"
    },
    {
        "type": "refactor",
        "module": "src.command_handler",
        "obj": "CommandHandler._extract_params",
        "line": 165,
        "column": 4,
        "endLine": 165,
        "endColumn": 23,
        "path": "src\\command_handler.py",
        "symbol": "too-many-branches",
        "message": "Too many branches (14/12)",
        "message-id": "R0912"
    },
    {
        "type": "warning",
        "module": "src.command_handler",
        "obj": "CommandHandler.to_api_request",
        "line": 251,
        "column": 8,
        "endLine": 251,
        "endColumn": 16,
        "path": "src\\command_handler.py",
        "symbol": "redefined-outer-name",
        "message": "Redefining name 'endpoint' from outer scope (line 289)",
        "message-id": "W0621"
    },
    {
        "type": "warning",
        "module": "src.command_handler",
        "obj": "CommandHandler.to_api_request",
        "line": 252,
        "column": 8,
        "endLine": 252,
        "endColumn": 12,
        "path": "src\\command_handler.py",
        "symbol": "redefined-outer-name",
        "message": "Redefining name 'body' from outer scope (line 289)",
        "message-id": "W0621"
    },
    {
        "type": "warning",
        "module": "src.command_handler",
        "obj": "parse_command",
        "line": 265,
        "column": 4,
        "endLine": 265,
        "endColumn": 11,
        "path": "src\\command_handler.py",
        "symbol": "redefined-outer-name",
        "message": "Redefining name 'handler' from outer scope (line 271)",
        "message-id": "W0621"
    },
    {
        "type": "warning",
        "module": "src.command_handler",
        "obj": "",
        "line": 7,
        "column": 0,
        "endLine": 7,
        "endColumn": 11,
        "path": "src\\command_handler.py",
        "symbol": "unused-import",
        "message": "Unused import json",
        "message-id": "W0611"
    },
    {
        "type": "warning",
        "module": "src.command_handler",
        "obj": "",
        "line": 8,
        "column": 0,
        "endLine": 8,
        "endColumn": 61,
        "path": "src\\command_handler.py",
        "symbol": "unused-import",
        "message": "Unused Optional imported from typing",
        "message-id": "W0611"
    },
    {
        "type": "warning",
        "module": "src.command_handler",
        "obj": "",
        "line": 8,
        "column": 0,
        "endLine": 8,
        "endColumn": 61,
        "path": "src\\command_handler.py",
        "symbol": "unused-import",
        "message": "Unused Callable imported from typing",
        "message-id": "W0611"
    },
    {
        "type": "convention",
        "module": "src.database",
        "obj": "",
        "line": 210,
        "column": 0,
        "endLine": null,
        "endColumn": null,
        "path": "src\\database.py",
        "symbol": "trailing-whitespace",
        "message": "Trailing whitespace",
        "message-id": "C0303"
    },
    {
        "type": "refactor",
        "module": "src.database",
        "obj": "DeviceRecord",
        "line": 31,
        "column": 0,
        "endLine": 31,
        "endColumn": 18,
        "path": "src\\database.py",
        "symbol": "too-many-instance-attributes",
        "message": "Too many instance attributes (10/7)",
        "message-id": "R0902"
    },
    {
        "type": "convention",
        "module": "src.database",
        "obj": "DeviceRecord.to_dict",
        "line": 44,
        "column": 4,
        "endLine": 44,
        "endColumn": 15,
        "path": "src\\database.py",
        "symbol": "missing-function-docstring",
        "message": "Missing function or method docstring",
        "message-id": "C0116"
    },
    {
        "type": "refactor",
        "module": "src.database",
        "obj": "ScriptRecord",
        "line": 60,
        "column": 0,
        "endLine": 60,
        "endColumn": 18,
        "path": "src\\database.py",
        "symbol": "too-many-instance-attributes",
        "message": "Too many instance attributes (8/7)",
        "message-id": "R0902"
    },
    {
        "type": "convention",
        "module": "src.database",
        "obj": "ScriptRecord.to_dict",
        "line": 71,
        "column": 4,
        "endLine": 71,
        "endColumn": 15,
        "path": "src\\database.py",
        "symbol": "missing-function-docstring",
        "message": "Missing function or method docstring",
        "message-id": "C0116"
    },
    {
        "type": "warning",
        "module": "src.database",
        "obj": "ScriptRecord.get_script_actions",
        "line": 87,
        "column": 15,
        "endLine": 87,
        "endColumn": 24,
        "path": "src\\database.py",
        "symbol": "broad-exception-caught",
        "message": "Catching too general exception Exception",
        "message-id": "W0718"
    },
    {
        "type": "convention",
        "module": "src.database",
        "obj": "OperationLogRecord.to_dict",
        "line": 102,
        "column": 4,
        "endLine": 102,
        "endColumn": 15,
        "path": "src\\database.py",
        "symbol": "missing-function-docstring",
        "message": "Missing function or method docstring",
        "message-id": "C0116"
    },
    {
        "type": "warning",
        "module": "src.database",
        "obj": "DatabaseManager._set_db_permissions",
        "line": 152,
        "column": 15,
        "endLine": 152,
        "endColumn": 24,
        "path": "src\\database.py",
        "symbol": "broad-exception-caught",
        "message": "Catching too general exception Exception",
        "message-id": "W0718"
    },
    {
        "type": "error",
        "module": "src.database",
        "obj": "DatabaseManager.delete_old_logs",
        "line": 462,
        "column": 35,
        "endLine": 462,
        "endColumn": 53,
        "path": "src\\database.py",
        "symbol": "no-member",
        "message": "Class 'datetime' has no 'timedelta' member",
        "message-id": "E1101"
    },
    {
        "type": "warning",
        "module": "src.database",
        "obj": "get_database_manager",
        "line": 501,
        "column": 4,
        "endLine": 501,
        "endColumn": 22,
        "path": "src\\database.py",
        "symbol": "global-statement",
        "message": "Using the global statement",
        "message-id": "W0603"
    },
    {
        "type": "refactor",
        "module": "src.device_manager",
        "obj": "Device",
        "line": 34,
        "column": 0,
        "endLine": 34,
        "endColumn": 12,
        "path": "src\\device_manager.py",
        "symbol": "too-many-instance-attributes",
        "message": "Too many instance attributes (8/7)",
        "message-id": "R0902"
    },
    {
        "type": "warning",
        "module": "src.device_manager",
        "obj": "DeviceManager._run_adb_command",
        "line": 100,
        "column": 15,
        "endLine": 100,
        "endColumn": 24,
        "path": "src\\device_manager.py",
        "symbol": "broad-exception-caught",
        "message": "Catching too general exception Exception",
        "message-id": "W0718"
    },
    {
        "type": "warning",
        "module": "src.device_manager",
        "obj": "DeviceManager._run_adb_command",
        "line": 91,
        "column": 21,
        "endLine": 96,
        "endColumn": 13,
        "path": "src\\device_manager.py",
        "symbol": "subprocess-run-check",
        "message": "'subprocess.run' used without explicitly defining the value for 'check'.",
        "message-id": "W1510"
    },
    {
        "type": "warning",
        "module": "src.device_manager",
        "obj": "DeviceManager._parse_device_line",
        "line": 155,
        "column": 8,
        "endLine": 155,
        "endColumn": 14,
        "path": "src\\device_manager.py",
        "symbol": "redefined-outer-name",
        "message": "Redefining name 'device' from outer scope (line 334)",
        "message-id": "W0621"
    },
    {
        "type": "warning",
        "module": "src.device_manager",
        "obj": "DeviceManager.list_devices",
        "line": 186,
        "column": 20,
        "endLine": 186,
        "endColumn": 26,
        "path": "src\\device_manager.py",
        "symbol": "redefined-outer-name",
        "message": "Redefining name 'device' from outer scope (line 334)",
        "message-id": "W0621"
    },
    {
        "type": "warning",
        "module": "src.device_manager",
        "obj": "DeviceManager.disconnect_device",
        "line": 266,
        "column": 21,
        "endLine": 266,
        "endColumn": 27,
        "path": "src\\device_manager.py",
        "symbol": "unused-variable",
        "message": "Unused variable 'stdout'",
        "message-id": "W0612"
    },
    {
        "type": "warning",
        "module": "src.device_manager",
        "obj": "",
        "line": 7,
        "column": 0,
        "endLine": 7,
        "endColumn": 9,
        "path": "src\\device_manager.py",
        "symbol": "unused-import",
        "message": "Unused import re",
        "message-id": "W0611"
    },
    {
        "type": "refactor",
        "module": "src.scrcpy_client",
        "obj": "ScrcpyConfig",
        "line": 39,
        "column": 0,
        "endLine": 39,
        "endColumn": 18,
        "path": "src\\scrcpy_client.py",
        "symbol": "too-many-instance-attributes",
        "message": "Too many instance attributes (8/7)",
        "message-id": "R0902"
    },
    {
        "type": "refactor",
        "module": "src.scrcpy_client",
        "obj": "ScrcpyClient",
        "line": 51,
        "column": 0,
        "endLine": 51,
        "endColumn": 18,
        "path": "src\\scrcpy_client.py",
        "symbol": "too-many-instance-attributes",
        "message": "Too many instance attributes (11/7)",
        "message-id": "R0902"
    },
    {
        "type": "warning",
        "module": "src.scrcpy_client",
        "obj": "ScrcpyClient.start",
        "line": 131,
        "column": 19,
        "endLine": 131,
        "endColumn": 28,
        "path": "src\\scrcpy_client.py",
        "symbol": "broad-exception-caught",
        "message": "Catching too general exception Exception",
        "message-id": "W0718"
    },
    {
        "type": "refactor",
        "module": "src.scrcpy_client",
        "obj": "ScrcpyClient.start",
        "line": 104,
        "column": 32,
        "endLine": 108,
        "endColumn": 17,
        "path": "src\\scrcpy_client.py",
        "symbol": "consider-using-with",
        "message": "Consider using 'with' for resource-allocating operations",
        "message-id": "R1732"
    },
    {
        "type": "warning",
        "module": "src.scrcpy_client",
        "obj": "ScrcpyClient._connect_video_socket",
        "line": 184,
        "column": 15,
        "endLine": 184,
        "endColumn": 24,
        "path": "src\\scrcpy_client.py",
        "symbol": "broad-exception-caught",
        "message": "Catching too general exception Exception",
        "message-id": "W0718"
    },
    {
        "type": "warning",
        "module": "src.scrcpy_client",
        "obj": "ScrcpyClient._connect_control_socket",
        "line": 197,
        "column": 15,
        "endLine": 197,
        "endColumn": 24,
        "path": "src\\scrcpy_client.py",
        "symbol": "broad-exception-caught",
        "message": "Catching too general exception Exception",
        "message-id": "W0718"
    },
    {
        "type": "warning",
        "module": "src.scrcpy_client",
        "obj": "ScrcpyClient._video_loop",
        "line": 210,
        "column": 19,
        "endLine": 210,
        "endColumn": 28,
        "path": "src\\scrcpy_client.py",
        "symbol": "broad-exception-caught",
        "message": "Catching too general exception Exception",
        "message-id": "W0718"
    },
    {
        "type": "warning",
        "module": "src.scrcpy_client",
        "obj": "ScrcpyClient.stop",
        "line": 224,
        "column": 16,
        "endLine": 225,
        "endColumn": 24,
        "path": "src\\scrcpy_client.py",
        "symbol": "bare-except",
        "message": "No exception type(s) specified",
        "message-id": "W0702"
    },
    {
        "type": "warning",
        "module": "src.scrcpy_client",
        "obj": "ScrcpyClient.stop",
        "line": 231,
        "column": 16,
        "endLine": 232,
        "endColumn": 24,
        "path": "src\\scrcpy_client.py",
        "symbol": "bare-except",
        "message": "No exception type(s) specified",
        "message-id": "W0702"
    },
    {
        "type": "warning",
        "module": "src.scrcpy_client",
        "obj": "ScrcpyClient.stop",
        "line": 240,
        "column": 16,
        "endLine": 244,
        "endColumn": 28,
        "path": "src\\scrcpy_client.py",
        "symbol": "bare-except",
        "message": "No exception type(s) specified",
        "message-id": "W0702"
    },
    {
        "type": "warning",
        "module": "src.scrcpy_client",
        "obj": "ScrcpyClient.stop",
        "line": 243,
        "column": 20,
        "endLine": 244,
        "endColumn": 28,
        "path": "src\\scrcpy_client.py",
        "symbol": "bare-except",
        "message": "No exception type(s) specified",
        "message-id": "W0702"
    },
    {
        "type": "warning",
        "module": "src.scrcpy_client",
        "obj": "ScrcpyClient.inject_event",
        "line": 270,
        "column": 15,
        "endLine": 270,
        "endColumn": 24,
        "path": "src\\scrcpy_client.py",
        "symbol": "broad-exception-caught",
        "message": "Catching too general exception Exception",
        "message-id": "W0718"
    },
    {
        "type": "refactor",
        "module": "src.scrcpy_client",
        "obj": "ScrcpyClient.inject_touch",
        "line": 303,
        "column": 4,
        "endLine": 303,
        "endColumn": 20,
        "path": "src\\scrcpy_client.py",
        "symbol": "too-many-arguments",
        "message": "Too many arguments (9/5)",
        "message-id": "R0913"
    },
    {
        "type": "warning",
        "module": "src.scrcpy_client",
        "obj": "ScrcpyClient.inject_touch",
        "line": 311,
        "column": 8,
        "endLine": 311,
        "endColumn": 21,
        "path": "src\\scrcpy_client.py",
        "symbol": "unused-argument",
        "message": "Unused argument 'pressure'",
        "message-id": "W0613"
    },
    {
        "type": "warning",
        "module": "src.scrcpy_client",
        "obj": "ScrcpyClient.inject_touch",
        "line": 312,
        "column": 8,
        "endLine": 312,
        "endColumn": 26,
        "path": "src\\scrcpy_client.py",
        "symbol": "unused-argument",
        "message": "Unused argument 'buttons_state'",
        "message-id": "W0613"
    },
    {
        "type": "warning",
        "module": "src.scrcpy_client",
        "obj": "",
        "line": 6,
        "column": 0,
        "endLine": 6,
        "endColumn": 9,
        "path": "src\\scrcpy_client.py",
        "symbol": "unused-import",
        "message": "Unused import os",
        "message-id": "W0611"
    },
    {
        "type": "warning",
        "module": "src.scrcpy_client",
        "obj": "",
        "line": 7,
        "column": 0,
        "endLine": 7,
        "endColumn": 9,
        "path": "src\\scrcpy_client.py",
        "symbol": "unused-import",
        "message": "Unused import re",
        "message-id": "W0611"
    },
    {
        "type": "warning",
        "module": "src.scrcpy_client",
        "obj": "",
        "line": 13,
        "column": 0,
        "endLine": 13,
        "endColumn": 61,
        "path": "src\\scrcpy_client.py",
        "symbol": "unused-import",
        "message": "Unused Tuple imported from typing",
        "message-id": "W0611"
    },
    {
        "type": "warning",
        "module": "src.scrcpy_client",
        "obj": "",
        "line": 13,
        "column": 0,
        "endLine": 13,
        "endColumn": 61,
        "path": "src\\scrcpy_client.py",
        "symbol": "unused-import",
        "message": "Unused Dict imported from typing",
        "message-id": "W0611"
    },
    {
        "type": "warning",
        "module": "src.scrcpy_client",
        "obj": "",
        "line": 13,
        "column": 0,
        "endLine": 13,
        "endColumn": 61,
        "path": "src\\scrcpy_client.py",
        "symbol": "unused-import",
        "message": "Unused Any imported from typing",
        "message-id": "W0611"
    },
    {
        "type": "warning",
        "module": "src.scrcpy_client",
        "obj": "",
        "line": 16,
        "column": 0,
        "endLine": 16,
        "endColumn": 24,
        "path": "src\\scrcpy_client.py",
        "symbol": "unused-import",
        "message": "Unused Path imported from pathlib",
        "message-id": "W0611"
    },
    {
        "type": "warning",
        "module": "src.scrcpy_client",
        "obj": "",
        "line": 18,
        "column": 0,
        "endLine": 18,
        "endColumn": 10,
        "path": "src\\scrcpy_client.py",
        "symbol": "unused-import",
        "message": "Unused import cv2",
        "message-id": "W0611"
    },
    {
        "type": "warning",
        "module": "src.screen",
        "obj": "ScreenController._check_ocr",
        "line": 86,
        "column": 15,
        "endLine": 86,
        "endColumn": 24,
        "path": "src\\screen.py",
        "symbol": "broad-exception-caught",
        "message": "Catching too general exception Exception",
        "message-id": "W0718"
    },
    {
        "type": "warning",
        "module": "src.screen",
        "obj": "ScreenController.screenshot",
        "line": 132,
        "column": 12,
        "endLine": 132,
        "endColumn": 17,
        "path": "src\\screen.py",
        "symbol": "redefined-outer-name",
        "message": "Redefining name 'image' from outer scope (line 428)",
        "message-id": "W0621"
    },
    {
        "type": "warning",
        "module": "src.screen",
        "obj": "ScreenController.screenshot",
        "line": 144,
        "column": 15,
        "endLine": 144,
        "endColumn": 24,
        "path": "src\\screen.py",
        "symbol": "broad-exception-caught",
        "message": "Catching too general exception Exception",
        "message-id": "W0718"
    },
    {
        "type": "warning",
        "module": "src.screen",
        "obj": "ScreenController.screenshot",
        "line": 124,
        "column": 21,
        "endLine": 124,
        "endColumn": 73,
        "path": "src\\screen.py",
        "symbol": "subprocess-run-check",
        "message": "'subprocess.run' used without explicitly defining the value for 'check'.",
        "message-id": "W1510"
    },
    {
        "type": "error",
        "module": "src.screen",
        "obj": "ScreenController.screenshot",
        "line": 132,
        "column": 20,
        "endLine": 132,
        "endColumn": 32,
        "path": "src\\screen.py",
        "symbol": "no-member",
        "message": "Module 'cv2' has no 'imdecode' member",
        "message-id": "E1101"
    },
    {
        "type": "error",
        "module": "src.screen",
        "obj": "ScreenController.screenshot",
        "line": 132,
        "column": 46,
        "endLine": 132,
        "endColumn": 62,
        "path": "src\\screen.py",
        "symbol": "no-member",
        "message": "Module 'cv2' has no 'IMREAD_COLOR' member",
        "message-id": "E1101"
    },
    {
        "type": "error",
        "module": "src.screen",
        "obj": "ScreenController.screenshot",
        "line": 140,
        "column": 16,
        "endLine": 140,
        "endColumn": 27,
        "path": "src\\screen.py",
        "symbol": "no-member",
        "message": "Module 'cv2' has no 'imwrite' member",
        "message-id": "E1101"
    },
    {
        "type": "warning",
        "module": "src.screen",
        "obj": "ScreenController.screenshot_to_base64",
        "line": 163,
        "column": 8,
        "endLine": 163,
        "endColumn": 13,
        "path": "src\\screen.py",
        "symbol": "redefined-outer-name",
        "message": "Redefining name 'image' from outer scope (line 428)",
        "message-id": "W0621"
    },
    {
        "type": "warning",
        "module": "src.screen",
        "obj": "ScreenController.screenshot_to_base64",
        "line": 176,
        "column": 15,
        "endLine": 176,
        "endColumn": 24,
        "path": "src\\screen.py",
        "symbol": "broad-exception-caught",
        "message": "Catching too general exception Exception",
        "message-id": "W0718"
    },
    {
        "type": "error",
        "module": "src.screen",
        "obj": "ScreenController.screenshot_to_base64",
        "line": 169,
        "column": 29,
        "endLine": 169,
        "endColumn": 53,
        "path": "src\\screen.py",
        "symbol": "no-member",
        "message": "Module 'cv2' has no 'IMWRITE_JPEG_QUALITY' member",
        "message-id": "E1101"
    },
    {
        "type": "error",
        "module": "src.screen",
        "obj": "ScreenController.screenshot_to_base64",
        "line": 170,
        "column": 24,
        "endLine": 170,
        "endColumn": 36,
        "path": "src\\screen.py",
        "symbol": "no-member",
        "message": "Module 'cv2' has no 'imencode' member",
        "message-id": "E1101"
    },
    {
        "type": "warning",
        "module": "src.screen",
        "obj": "ScreenController.ocr_text",
        "line": 183,
        "column": 8,
        "endLine": 183,
        "endColumn": 35,
        "path": "src\\screen.py",
        "symbol": "redefined-outer-name",
        "message": "Redefining name 'image' from outer scope (line 428)",
        "message-id": "W0621"
    },
    {
        "type": "warning",
        "module": "src.screen",
        "obj": "ScreenController.ocr_text",
        "line": 217,
        "column": 12,
        "endLine": 217,
        "endColumn": 19,
        "path": "src\\screen.py",
        "symbol": "redefined-outer-name",
        "message": "Redefining name 'results' from outer scope (line 434)",
        "message-id": "W0621"
    },
    {
        "type": "warning",
        "module": "src.screen",
        "obj": "ScreenController.ocr_text",
        "line": 236,
        "column": 15,
        "endLine": 236,
        "endColumn": 24,
        "path": "src\\screen.py",
        "symbol": "broad-exception-caught",
        "message": "Catching too general exception Exception",
        "message-id": "W0718"
    },
    {
        "type": "error",
        "module": "src.screen",
        "obj": "ScreenController.ocr_text",
        "line": 207,
        "column": 40,
        "endLine": 207,
        "endColumn": 52,
        "path": "src\\screen.py",
        "symbol": "no-member",
        "message": "Module 'cv2' has no 'cvtColor' member",
        "message-id": "E1101"
    },
    {
        "type": "error",
        "module": "src.screen",
        "obj": "ScreenController.ocr_text",
        "line": 207,
        "column": 60,
        "endLine": 207,
        "endColumn": 77,
        "path": "src\\screen.py",
        "symbol": "no-member",
        "message": "Module 'cv2' has no 'COLOR_BGR2RGB' member",
        "message-id": "E1101"
    },
    {
        "type": "warning",
        "module": "src.screen",
        "obj": "ScreenController.find_text_position",
        "line": 244,
        "column": 8,
        "endLine": 244,
        "endColumn": 35,
        "path": "src\\screen.py",
        "symbol": "redefined-outer-name",
        "message": "Redefining name 'image' from outer scope (line 428)",
        "message-id": "W0621"
    },
    {
        "type": "warning",
        "module": "src.screen",
        "obj": "ScreenController.find_text_position",
        "line": 259,
        "column": 8,
        "endLine": 259,
        "endColumn": 15,
        "path": "src\\screen.py",
        "symbol": "redefined-outer-name",
        "message": "Redefining name 'results' from outer scope (line 434)",
        "message-id": "W0621"
    },
    {
        "type": "warning",
        "module": "src.screen",
        "obj": "ScreenController.find_text_position",
        "line": 261,
        "column": 12,
        "endLine": 261,
        "endColumn": 17,
        "path": "src\\screen.py",
        "symbol": "redefined-outer-name",
        "message": "Redefining name 'match' from outer scope (line 436)",
        "message-id": "W0621"
    },
    {
        "type": "warning",
        "module": "src.screen",
        "obj": "ScreenController.click_by_text",
        "line": 308,
        "column": 8,
        "endLine": 308,
        "endColumn": 13,
        "path": "src\\screen.py",
        "symbol": "redefined-outer-name",
        "message": "Redefining name 'match' from outer scope (line 436)",
        "message-id": "W0621"
    },
    {
        "type": "warning",
        "module": "src.screen",
        "obj": "ScreenController.draw_text_boxes",
        "line": 320,
        "column": 8,
        "endLine": 320,
        "endColumn": 25,
        "path": "src\\screen.py",
        "symbol": "redefined-outer-name",
        "message": "Redefining name 'image' from outer scope (line 428)",
        "message-id": "W0621"
    },
    {
        "type": "warning",
        "module": "src.screen",
        "obj": "ScreenController.draw_text_boxes",
        "line": 339,
        "column": 12,
        "endLine": 339,
        "endColumn": 17,
        "path": "src\\screen.py",
        "symbol": "redefined-outer-name",
        "message": "Redefining name 'match' from outer scope (line 436)",
        "message-id": "W0621"
    },
    {
        "type": "error",
        "module": "src.screen",
        "obj": "ScreenController.draw_text_boxes",
        "line": 341,
        "column": 12,
        "endLine": 341,
        "endColumn": 25,
        "path": "src\\screen.py",
        "symbol": "no-member",
        "message": "Module 'cv2' has no 'rectangle' member",
        "message-id": "E1101"
    },
    {
        "type": "error",
        "module": "src.screen",
        "obj": "ScreenController.draw_text_boxes",
        "line": 351,
        "column": 12,
        "endLine": 351,
        "endColumn": 23,
        "path": "src\\screen.py",
        "symbol": "no-member",
        "message": "Module 'cv2' has no 'putText' member",
        "message-id": "E1101"
    },
    {
        "type": "error",
        "module": "src.screen",
        "obj": "ScreenController.draw_text_boxes",
        "line": 355,
        "column": 16,
        "endLine": 355,
        "endColumn": 40,
        "path": "src\\screen.py",
        "symbol": "no-member",
        "message": "Module 'cv2' has no 'FONT_HERSHEY_SIMPLEX' member",
        "message-id": "E1101"
    },
    {
        "type": "warning",
        "module": "src.screen",
        "obj": "ScreenController.preprocess_image",
        "line": 365,
        "column": 8,
        "endLine": 365,
        "endColumn": 25,
        "path": "src\\screen.py",
        "symbol": "redefined-outer-name",
        "message": "Redefining name 'image' from outer scope (line 428)",
        "message-id": "W0621"
    },
    {
        "type": "error",
        "module": "src.screen",
        "obj": "ScreenController.preprocess_image",
        "line": 386,
        "column": 21,
        "endLine": 386,
        "endColumn": 40,
        "path": "src\\screen.py",
        "symbol": "no-member",
        "message": "Module 'cv2' has no 'convertScaleAbs' member",
        "message-id": "E1101"
    },
    {
        "type": "error",
        "module": "src.screen",
        "obj": "ScreenController.preprocess_image",
        "line": 390,
        "column": 21,
        "endLine": 390,
        "endColumn": 52,
        "path": "src\\screen.py",
        "symbol": "no-member",
        "message": "Module 'cv2' has no 'fastNlMeansDenoisingColored' member",
        "message-id": "E1101"
    },
    {
        "type": "error",
        "module": "src.screen",
        "obj": "ScreenController.preprocess_image",
        "line": 394,
        "column": 21,
        "endLine": 394,
        "endColumn": 33,
        "path": "src\\screen.py",
        "symbol": "no-member",
        "message": "Module 'cv2' has no 'cvtColor' member",
        "message-id": "E1101"
    },
    {
        "type": "error",
        "module": "src.screen",
        "obj": "ScreenController.preprocess_image",
        "line": 394,
        "column": 42,
        "endLine": 394,
        "endColumn": 60,
        "path": "src\\screen.py",
        "symbol": "no-member",
        "message": "Module 'cv2' has no 'COLOR_BGR2GRAY' member",
        "message-id": "E1101"
    },
    {
        "type": "error",
        "module": "src.screen",
        "obj": "",
        "line": 421,
        "column": 4,
        "endLine": 421,
        "endColumn": 49,
        "path": "src\\screen.py",
        "symbol": "import-error",
        "message": "Unable to import 'device_manager'",
        "message-id": "E0401"
    },
    {
        "type": "error",
        "module": "src.screen",
        "obj": "",
        "line": 422,
        "column": 4,
        "endLine": 422,
        "endColumn": 41,
        "path": "src\\screen.py",
        "symbol": "import-error",
        "message": "Unable to import 'adb_client'",
        "message-id": "E0401"
    },
    {
        "type": "warning",
        "module": "src.screen",
        "obj": "",
        "line": 6,
        "column": 0,
        "endLine": 6,
        "endColumn": 9,
        "path": "src\\screen.py",
        "symbol": "unused-import",
        "message": "Unused import io",
        "message-id": "W0611"
    },
    {
        "type": "warning",
        "module": "src.screen",
        "obj": "",
        "line": 7,
        "column": 0,
        "endLine": 7,
        "endColumn": 9,
        "path": "src\\screen.py",
        "symbol": "unused-import",
        "message": "Unused import os",
        "message-id": "W0611"
    },
    {
        "type": "warning",
        "module": "src.screen",
        "obj": "",
        "line": 8,
        "column": 0,
        "endLine": 8,
        "endColumn": 9,
        "path": "src\\screen.py",
        "symbol": "unused-import",
        "message": "Unused import re",
        "message-id": "W0611"
    },
    {
        "type": "warning",
        "module": "src.screen",
        "obj": "",
        "line": 10,
        "column": 0,
        "endLine": 10,
        "endColumn": 15,
        "path": "src\\screen.py",
        "symbol": "unused-import",
        "message": "Unused import tempfile",
        "message-id": "W0611"
    },
    {
        "type": "warning",
        "module": "src.screen",
        "obj": "",
        "line": 12,
        "column": 0,
        "endLine": 12,
        "endColumn": 53,
        "path": "src\\screen.py",
        "symbol": "unused-import",
        "message": "Unused Dict imported from typing",
        "message-id": "W0611"
    },
    {
        "type": "warning",
        "module": "src.screen",
        "obj": "",
        "line": 12,
        "column": 0,
        "endLine": 12,
        "endColumn": 53,
        "path": "src\\screen.py",
        "symbol": "unused-import",
        "message": "Unused Union imported from typing",
        "message-id": "W0611"
    },
    {
        "type": "warning",
        "module": "src.screen",
        "obj": "",
        "line": 14,
        "column": 0,
        "endLine": 14,
        "endColumn": 24,
        "path": "src\\screen.py",
        "symbol": "unused-import",
        "message": "Unused Path imported from pathlib",
        "message-id": "W0611"
    },
    {
        "type": "warning",
        "module": "src.screen",
        "obj": "",
        "line": 18,
        "column": 0,
        "endLine": 18,
        "endColumn": 43,
        "path": "src\\screen.py",
        "symbol": "unused-import",
        "message": "Unused ImageDraw imported from PIL",
        "message-id": "W0611"
    },
    {
        "type": "warning",
        "module": "src.screen",
        "obj": "",
        "line": 18,
        "column": 0,
        "endLine": 18,
        "endColumn": 43,
        "path": "src\\screen.py",
        "symbol": "unused-import",
        "message": "Unused ImageFont imported from PIL",
        "message-id": "W0611"
    },
    {
        "type": "warning",
        "module": "src.screen",
        "obj": "",
        "line": 28,
        "column": 0,
        "endLine": 28,
        "endColumn": 49,
        "path": "src\\screen.py",
        "symbol": "unused-import",
        "message": "Unused Device imported from device_manager",
        "message-id": "W0611"
    },
    {
        "type": "convention",
        "module": "src.script_recorder",
        "obj": "RecordedAction.to_dict",
        "line": 34,
        "column": 4,
        "endLine": 34,
        "endColumn": 15,
        "path": "src\\script_recorder.py",
        "symbol": "missing-function-docstring",
        "message": "Missing function or method docstring",
        "message-id": "C0116"
    },
    {
        "type": "refactor",
        "module": "src.script_recorder",
        "obj": "ScriptRecorder",
        "line": 45,
        "column": 0,
        "endLine": 45,
        "endColumn": 20,
        "path": "src\\script_recorder.py",
        "symbol": "too-many-instance-attributes",
        "message": "Too many instance attributes (10/7)",
        "message-id": "R0902"
    },
    {
        "type": "refactor",
        "module": "src.script_recorder",
        "obj": "ScriptRecorder.record_swipe",
        "line": 209,
        "column": 4,
        "endLine": 209,
        "endColumn": 20,
        "path": "src\\script_recorder.py",
        "symbol": "too-many-arguments",
        "message": "Too many arguments (7/5)",
        "message-id": "R0913"
    },
    {
        "type": "warning",
        "module": "src.script_recorder",
        "obj": "",
        "line": 13,
        "column": 0,
        "endLine": 13,
        "endColumn": 55,
        "path": "src\\script_recorder.py",
        "symbol": "unused-import",
        "message": "Unused DeviceStatus imported from device_manager",
        "message-id": "W0611"
    },
    {
        "type": "warning",
        "module": "src.script_recorder",
        "obj": "",
        "line": 14,
        "column": 0,
        "endLine": 14,
        "endColumn": 49,
        "path": "src\\script_recorder.py",
        "symbol": "unused-import",
        "message": "Unused ADBClient imported from adb_client",
        "message-id": "W0611"
    },
    {
        "type": "error",
        "module": "src.script_runner",
        "obj": "ScriptRunner.validate_script",
        "line": 70,
        "column": 65,
        "endLine": 70,
        "endColumn": 70,
        "path": "src\\script_runner.py",
        "symbol": "undefined-variable",
        "message": "Undefined variable 'Tuple'",
        "message-id": "E0602"
    },
    {
        "type": "warning",
        "module": "src.script_runner",
        "obj": "ScriptRunner.validate_script",
        "line": 111,
        "column": 15,
        "endLine": 111,
        "endColumn": 24,
        "path": "src\\script_runner.py",
        "symbol": "broad-exception-caught",
        "message": "Catching too general exception Exception",
        "message-id": "W0718"
    },
    {
        "type": "refactor",
        "module": "src.script_runner",
        "obj": "ScriptRunner.validate_script",
        "line": 70,
        "column": 4,
        "endLine": 70,
        "endColumn": 23,
        "path": "src\\script_runner.py",
        "symbol": "too-many-return-statements",
        "message": "Too many return statements (8/6)",
        "message-id": "R0911"
    },
    {
        "type": "warning",
        "module": "src.script_runner",
        "obj": "ScriptRunner.execute_script",
        "line": 130,
        "column": 8,
        "endLine": 130,
        "endColumn": 16,
        "path": "src\\script_runner.py",
        "symbol": "redefined-outer-name",
        "message": "Redefining name 'is_valid' from outer scope (line 710)",
        "message-id": "W0621"
    },
    {
        "type": "warning",
        "module": "src.script_runner",
        "obj": "ScriptRunner.execute_script",
        "line": 130,
        "column": 18,
        "endLine": 130,
        "endColumn": 25,
        "path": "src\\script_runner.py",
        "symbol": "redefined-outer-name",
        "message": "Redefining name 'message' from outer scope (line 710)",
        "message-id": "W0621"
    },
    {
        "type": "warning",
        "module": "src.script_runner",
        "obj": "ScriptRunner._execute_action",
        "line": 217,
        "column": 15,
        "endLine": 217,
        "endColumn": 24,
        "path": "src\\script_runner.py",
        "symbol": "broad-exception-caught",
        "message": "Catching too general exception Exception",
        "message-id": "W0718"
    },
    {
        "type": "refactor",
        "module": "src.script_runner",
        "obj": "ScriptRunner._execute_action",
        "line": 182,
        "column": 12,
        "endLine": 215,
        "endColumn": 17,
        "path": "src\\script_runner.py",
        "symbol": "no-else-return",
        "message": "Unnecessary \"elif\" after \"return\", remove the leading \"el\" from \"elif\"",
        "message-id": "R1705"
    },
    {
        "type": "refactor",
        "module": "src.script_runner",
        "obj": "ScriptRunner._execute_action",
        "line": 161,
        "column": 4,
        "endLine": 161,
        "endColumn": 23,
        "path": "src\\script_runner.py",
        "symbol": "too-many-return-statements",
        "message": "Too many return statements (11/6)",
        "message-id": "R0911"
    },
    {
        "type": "refactor",
        "module": "src.script_runner",
        "obj": "ScriptRunner._execute_click",
        "line": 247,
        "column": 12,
        "endLine": 261,
        "endColumn": 17,
        "path": "src\\script_runner.py",
        "symbol": "no-else-return",
        "message": "Unnecessary \"else\" after \"return\", remove the \"else\" and de-indent the code inside it",
        "message-id": "R1705"
    },
    {
        "type": "refactor",
        "module": "src.script_runner",
        "obj": "ScriptRunner._execute_click",
        "line": 265,
        "column": 12,
        "endLine": 279,
        "endColumn": 17,
        "path": "src\\script_runner.py",
        "symbol": "no-else-return",
        "message": "Unnecessary \"else\" after \"return\", remove the \"else\" and de-indent the code inside it",
        "message-id": "R1705"
    },
    {
        "type": "refactor",
        "module": "src.script_runner",
        "obj": "ScriptRunner._execute_swipe",
        "line": 317,
        "column": 8,
        "endLine": 335,
        "endColumn": 13,
        "path": "src\\script_runner.py",
        "symbol": "no-else-return",
        "message": "Unnecessary \"else\" after \"return\", remove the \"else\" and de-indent the code inside it",
        "message-id": "R1705"
    },
    {
        "type": "refactor",
        "module": "src.script_runner",
        "obj": "ScriptRunner._execute_input",
        "line": 356,
        "column": 8,
        "endLine": 370,
        "endColumn": 13,
        "path": "src\\script_runner.py",
        "symbol": "no-else-return",
        "message": "Unnecessary \"else\" after \"return\", remove the \"else\" and de-indent the code inside it",
        "message-id": "R1705"
    },
    {
        "type": "refactor",
        "module": "src.script_runner",
        "obj": "ScriptRunner._execute_key",
        "line": 391,
        "column": 8,
        "endLine": 405,
        "endColumn": 13,
        "path": "src\\script_runner.py",
        "symbol": "no-else-return",
        "message": "Unnecessary \"else\" after \"return\", remove the \"else\" and de-indent the code inside it",
        "message-id": "R1705"
    },
    {
        "type": "warning",
        "module": "src.script_runner",
        "obj": "ScriptRunner._execute_sleep",
        "line": 424,
        "column": 15,
        "endLine": 424,
        "endColumn": 24,
        "path": "src\\script_runner.py",
        "symbol": "broad-exception-caught",
        "message": "Catching too general exception Exception",
        "message-id": "W0718"
    },
    {
        "type": "refactor",
        "module": "src.script_runner",
        "obj": "ScriptRunner._execute_app",
        "line": 452,
        "column": 12,
        "endLine": 466,
        "endColumn": 17,
        "path": "src\\script_runner.py",
        "symbol": "no-else-return",
        "message": "Unnecessary \"else\" after \"return\", remove the \"else\" and de-indent the code inside it",
        "message-id": "R1705"
    },
    {
        "type": "refactor",
        "module": "src.script_runner",
        "obj": "ScriptRunner._execute_app",
        "line": 470,
        "column": 12,
        "endLine": 484,
        "endColumn": 17,
        "path": "src\\script_runner.py",
        "symbol": "no-else-return",
        "message": "Unnecessary \"else\" after \"return\", remove the \"else\" and de-indent the code inside it",
        "message-id": "R1705"
    },
    {
        "type": "refactor",
        "module": "src.script_runner",
        "obj": "ScriptRunner._execute_screenshot",
        "line": 505,
        "column": 8,
        "endLine": 525,
        "endColumn": 13,
        "path": "src\\script_runner.py",
        "symbol": "no-else-return",
        "message": "Unnecessary \"else\" after \"return\", remove the \"else\" and de-indent the code inside it",
        "message-id": "R1705"
    },
    {
        "type": "warning",
        "module": "src.script_runner",
        "obj": "ScriptRunner._execute_ocr",
        "line": 529,
        "column": 8,
        "endLine": 529,
        "endColumn": 30,
        "path": "src\\script_runner.py",
        "symbol": "unused-argument",
        "message": "Unused argument 'params'",
        "message-id": "W0613"
    },
    {
        "type": "refactor",
        "module": "src.script_runner",
        "obj": "ScriptRunner._execute_find_text",
        "line": 582,
        "column": 8,
        "endLine": 620,
        "endColumn": 13,
        "path": "src\\script_runner.py",
        "symbol": "no-else-return",
        "message": "Unnecessary \"else\" after \"return\", remove the \"else\" and de-indent the code inside it",
        "message-id": "R1705"
    },
    {
        "type": "error",
        "module": "src.script_runner",
        "obj": "",
        "line": 703,
        "column": 4,
        "endLine": 703,
        "endColumn": 49,
        "path": "src\\script_runner.py",
        "symbol": "import-error",
        "message": "Unable to import 'device_manager'",
        "message-id": "E0401"
    },
    {
        "type": "warning",
        "module": "src.script_runner",
        "obj": "",
        "line": 9,
        "column": 0,
        "endLine": 9,
        "endColumn": 61,
        "path": "src\\script_runner.py",
        "symbol": "unused-import",
        "message": "Unused Callable imported from typing",
        "message-id": "W0611"
    },
    {
        "type": "warning",
        "module": "src.script_runner",
        "obj": "",
        "line": 14,
        "column": 0,
        "endLine": 14,
        "endColumn": 56,
        "path": "src\\script_runner.py",
        "symbol": "unused-import",
        "message": "Unused ADBClient imported from adb_client",
        "message-id": "W0611"
    },
    {
        "type": "warning",
        "module": "src.script_runner",
        "obj": "",
        "line": 15,
        "column": 0,
        "endLine": 15,
        "endColumn": 59,
        "path": "src\\script_runner.py",
        "symbol": "unused-import",
        "message": "Unused ScreenController imported from screen",
        "message-id": "W0611"
    },
    {
        "type": "convention",
        "module": "main",
        "obj": "",
        "line": 329,
        "column": 0,
        "endLine": null,
        "endColumn": null,
        "path": "main.py",
        "symbol": "trailing-whitespace",
        "message": "Trailing whitespace",
        "message-id": "C0303"
    },
    {
        "type": "convention",
        "module": "main",
        "obj": "",
        "line": 332,
        "column": 0,
        "endLine": null,
        "endColumn": null,
        "path": "main.py",
        "symbol": "trailing-whitespace",
        "message": "Trailing whitespace",
        "message-id": "C0303"
    },
    {
        "type": "convention",
        "module": "main",
        "obj": "",
        "line": 385,
        "column": 0,
        "endLine": null,
        "endColumn": null,
        "path": "main.py",
        "symbol": "trailing-whitespace",
        "message": "Trailing whitespace",
        "message-id": "C0303"
    },
    {
        "type": "convention",
        "module": "main",
        "obj": "",
        "line": 407,
        "column": 0,
        "endLine": null,
        "endColumn": null,
        "path": "main.py",
        "symbol": "trailing-whitespace",
        "message": "Trailing whitespace",
        "message-id": "C0303"
    },
    {
        "type": "convention",
        "module": "main",
        "obj": "",
        "line": 650,
        "column": 0,
        "endLine": null,
        "endColumn": null,
        "path": "main.py",
        "symbol": "line-too-long",
        "message": "Line too long (125/120)",
        "message-id": "C0301"
    },
    {
        "type": "convention",
        "module": "main",
        "obj": "",
        "line": 1,
        "column": 0,
        "endLine": null,
        "endColumn": null,
        "path": "main.py",
        "symbol": "too-many-lines",
        "message": "Too many lines in module (1129/1000)",
        "message-id": "C0302"
    },
    {
        "type": "convention",
        "module": "main",
        "obj": "",
        "line": 20,
        "column": 0,
        "endLine": 20,
        "endColumn": 109,
        "path": "main.py",
        "symbol": "wrong-import-position",
        "message": "Import \"from fastapi import FastAPI, HTTPException, Request, Response, WebSocket, WebSocketDisconnect, Depends, Query\" should be placed at the top of the module",
        "message-id": "C0413"
    },
    {
        "type": "convention",
        "module": "main",
        "obj": "",
        "line": 21,
        "column": 0,
        "endLine": 21,
        "endColumn": 50,
        "path": "main.py",
        "symbol": "wrong-import-position",
        "message": "Import \"from fastapi.middleware.cors import CORSMiddleware\" should be placed at the top of the module",
        "message-id": "C0413"
    },
    {
        "type": "convention",
        "module": "main",
        "obj": "",
        "line": 22,
        "column": 0,
        "endLine": 22,
        "endColumn": 56,
        "path": "main.py",
        "symbol": "wrong-import-position",
        "message": "Import \"from fastapi.responses import JSONResponse, FileResponse\" should be placed at the top of the module",
        "message-id": "C0413"
    },
    {
        "type": "convention",
        "module": "main",
        "obj": "",
        "line": 23,
        "column": 0,
        "endLine": 23,
        "endColumn": 43,
        "path": "main.py",
        "symbol": "wrong-import-position",
        "message": "Import \"from fastapi.staticfiles import StaticFiles\" should be placed at the top of the module",
        "message-id": "C0413"
    },
    {
        "type": "convention",
        "module": "main",
        "obj": "",
        "line": 24,
        "column": 0,
        "endLine": 24,
        "endColumn": 62,
        "path": "main.py",
        "symbol": "wrong-import-position",
        "message": "Import \"from fastapi.security.api_key import APIKeyQuery, APIKeyHeader\" should be placed at the top of the module",
        "message-id": "C0413"
    },
    {
        "type": "convention",
        "module": "main",
        "obj": "",
        "line": 25,
        "column": 0,
        "endLine": 25,
        "endColumn": 37,
        "path": "main.py",
        "symbol": "wrong-import-position",
        "message": "Import \"from pydantic import BaseModel, Field\" should be placed at the top of the module",
        "message-id": "C0413"
    },
    {
        "type": "convention",
        "module": "main",
        "obj": "",
        "line": 28,
        "column": 0,
        "endLine": 28,
        "endColumn": 57,
        "path": "main.py",
        "symbol": "wrong-import-position",
        "message": "Import \"from slowapi import Limiter, _rate_limit_exceeded_handler\" should be placed at the top of the module",
        "message-id": "C0413"
    },
    {
        "type": "convention",
        "module": "main",
        "obj": "",
        "line": 29,
        "column": 0,
        "endLine": 29,
        "endColumn": 43,
        "path": "main.py",
        "symbol": "wrong-import-position",
        "message": "Import \"from slowapi.util import get_remote_address\" should be placed at the top of the module",
        "message-id": "C0413"
    },
    {
        "type": "convention",
        "module": "main",
        "obj": "",
        "line": 30,
        "column": 0,
        "endLine": 30,
        "endColumn": 44,
        "path": "main.py",
        "symbol": "wrong-import-position",
        "message": "Import \"from slowapi.errors import RateLimitExceeded\" should be placed at the top of the module",
        "message-id": "C0413"
    },
    {
        "type": "convention",
        "module": "main",
        "obj": "",
        "line": 32,
        "column": 0,
        "endLine": 32,
        "endColumn": 78,
        "path": "main.py",
        "symbol": "wrong-import-position",
        "message": "Import \"from src.device_manager import DeviceManager, get_device_manager, DeviceStatus\" should be placed at the top of the module",
        "message-id": "C0413"
    },
    {
        "type": "convention",
        "module": "main",
        "obj": "",
        "line": 33,
        "column": 0,
        "endLine": 33,
        "endColumn": 59,
        "path": "main.py",
        "symbol": "wrong-import-position",
        "message": "Import \"from src.adb_client import ADBClient, Point, get_adb_client\" should be placed at the top of the module",
        "message-id": "C0413"
    },
    {
        "type": "convention",
        "module": "main",
        "obj": "",
        "line": 34,
        "column": 0,
        "endLine": 34,
        "endColumn": 62,
        "path": "main.py",
        "symbol": "wrong-import-position",
        "message": "Import \"from src.screen import ScreenController, get_screen_controller\" should be placed at the top of the module",
        "message-id": "C0413"
    },
    {
        "type": "convention",
        "module": "main",
        "obj": "",
        "line": 35,
        "column": 0,
        "endLine": 35,
        "endColumn": 73,
        "path": "main.py",
        "symbol": "wrong-import-position",
        "message": "Import \"from src.script_runner import ScriptRunner, get_script_runner, ActionType\" should be placed at the top of the module",
        "message-id": "C0413"
    },
    {
        "type": "error",
        "module": "main",
        "obj": "",
        "line": 35,
        "column": 0,
        "endLine": 35,
        "endColumn": 73,
        "path": "main.py",
        "symbol": "no-name-in-module",
        "message": "No name 'get_script_runner' in module 'src.script_runner'",
        "message-id": "E0611"
    },
    {
        "type": "convention",
        "module": "main",
        "obj": "",
        "line": 36,
        "column": 0,
        "endLine": 36,
        "endColumn": 67,
        "path": "main.py",
        "symbol": "wrong-import-position",
        "message": "Import \"from src.script_recorder import ScriptRecorder, get_script_recorder\" should be placed at the top of the module",
        "message-id": "C0413"
    },
    {
        "type": "convention",
        "module": "main",
        "obj": "",
        "line": 37,
        "column": 0,
        "endLine": 43,
        "endColumn": 1,
        "path": "main.py",
        "symbol": "wrong-import-position",
        "message": "Import \"from src.database import get_database_manager, DatabaseManager, DeviceRecord, ScriptRecord, OperationLogRecord\" should be placed at the top of the module",
        "message-id": "C0413"
    },
    {
        "type": "warning",
        "module": "main",
        "obj": "get_api_key",
        "line": 63,
        "column": 4,
        "endLine": 63,
        "endColumn": 22,
        "path": "main.py",
        "symbol": "redefined-outer-name",
        "message": "Redefining name 'api_key_query' from outer scope (line 59)",
        "message-id": "W0621"
    },
    {
        "type": "warning",
        "module": "main",
        "obj": "get_api_key",
        "line": 64,
        "column": 4,
        "endLine": 64,
        "endColumn": 23,
        "path": "main.py",
        "symbol": "redefined-outer-name",
        "message": "Redefining name 'api_key_header' from outer scope (line 60)",
        "message-id": "W0621"
    },
    {
        "type": "refactor",
        "module": "main",
        "obj": "get_api_key",
        "line": 67,
        "column": 7,
        "endLine": 67,
        "endColumn": 60,
        "path": "main.py",
        "symbol": "consider-using-in",
        "message": "Consider merging these comparisons with 'in' by using 'API_KEY in (api_key_query, api_key_header)'. Use a set instead if elements are hashable.",
        "message-id": "R1714"
    },
    {
        "type": "warning",
        "module": "main",
        "obj": "ConnectionManager.broadcast",
        "line": 229,
        "column": 19,
        "endLine": 229,
        "endColumn": 28,
        "path": "main.py",
        "symbol": "broad-exception-caught",
        "message": "Catching too general exception Exception",
        "message-id": "W0718"
    },
    {
        "type": "warning",
        "module": "main",
        "obj": "ConnectionManager.broadcast_to_device",
        "line": 238,
        "column": 23,
        "endLine": 238,
        "endColumn": 32,
        "path": "main.py",
        "symbol": "broad-exception-caught",
        "message": "Catching too general exception Exception",
        "message-id": "W0718"
    },
    {
        "type": "warning",
        "module": "main",
        "obj": "lifespan",
        "line": 252,
        "column": 19,
        "endLine": 252,
        "endColumn": 31,
        "path": "main.py",
        "symbol": "redefined-outer-name",
        "message": "Redefining name 'app' from outer scope (line 265)",
        "message-id": "W0621"
    },
    {
        "type": "warning",
        "module": "main",
        "obj": "lifespan",
        "line": 255,
        "column": 4,
        "endLine": 255,
        "endColumn": 39,
        "path": "main.py",
        "symbol": "logging-fstring-interpolation",
        "message": "Use lazy % formatting in logging functions",
        "message-id": "W1203"
    },
    {
        "type": "warning",
        "module": "main",
        "obj": "lifespan",
        "line": 257,
        "column": 8,
        "endLine": 257,
        "endColumn": 66,
        "path": "main.py",
        "symbol": "logging-fstring-interpolation",
        "message": "Use lazy % formatting in logging functions",
        "message-id": "W1203"
    },
    {
        "type": "warning",
        "module": "main",
        "obj": "lifespan",
        "line": 252,
        "column": 19,
        "endLine": 252,
        "endColumn": 31,
        "path": "main.py",
        "symbol": "unused-argument",
        "message": "Unused argument 'app'",
        "message-id": "W0613"
    },
    {
        "type": "convention",
        "module": "main",
        "obj": "add_security_headers",
        "line": 281,
        "column": 0,
        "endLine": 281,
        "endColumn": 30,
        "path": "main.py",
        "symbol": "missing-function-docstring",
        "message": "Missing function or method docstring",
        "message-id": "C0116"
    },
    {
        "type": "warning",
        "module": "main",
        "obj": "global_exception_handler",
        "line": 328,
        "column": 4,
        "endLine": 328,
        "endColumn": 62,
        "path": "main.py",
        "symbol": "logging-fstring-interpolation",
        "message": "Use lazy % formatting in logging functions",
        "message-id": "W1203"
    },
    {
        "type": "warning",
        "module": "main",
        "obj": "global_exception_handler",
        "line": 326,
        "column": 35,
        "endLine": 326,
        "endColumn": 51,
        "path": "main.py",
        "symbol": "unused-argument",
        "message": "Unused argument 'request'",
        "message-id": "W0613"
    },
    {
        "type": "refactor",
        "module": "main",
        "obj": "log_operation",
        "line": 363,
        "column": 0,
        "endLine": 363,
        "endColumn": 17,
        "path": "main.py",
        "symbol": "too-many-arguments",
        "message": "Too many arguments (7/5)",
        "message-id": "R0913"
    },
    {
        "type": "warning",
        "module": "main",
        "obj": "log_operation",
        "line": 394,
        "column": 11,
        "endLine": 394,
        "endColumn": 20,
        "path": "main.py",
        "symbol": "broad-exception-caught",
        "message": "Catching too general exception Exception",
        "message-id": "W0718"
    },
    {
        "type": "warning",
        "module": "main",
        "obj": "log_operation",
        "line": 381,
        "column": 16,
        "endLine": 382,
        "endColumn": 60,
        "path": "main.py",
        "symbol": "bare-except",
        "message": "No exception type(s) specified",
        "message-id": "W0702"
    },
    {
        "type": "warning",
        "module": "main",
        "obj": "log_operation",
        "line": 395,
        "column": 8,
        "endLine": 395,
        "endColumn": 48,
        "path": "main.py",
        "symbol": "logging-fstring-interpolation",
        "message": "Use lazy % formatting in logging functions",
        "message-id": "W1203"
    },
    {
        "type": "warning",
        "module": "main",
        "obj": "websocket_endpoint",
        "line": 443,
        "column": 11,
        "endLine": 443,
        "endColumn": 20,
        "path": "main.py",
        "symbol": "broad-exception-caught",
        "message": "Catching too general exception Exception",
        "message-id": "W0718"
    },
    {
        "type": "warning",
        "module": "main",
        "obj": "websocket_endpoint",
        "line": 444,
        "column": 8,
        "endLine": 444,
        "endColumn": 45,
        "path": "main.py",
        "symbol": "logging-fstring-interpolation",
        "message": "Use lazy % formatting in logging functions",
        "message-id": "W1203"
    },
    {
        "type": "error",
        "module": "main",
        "obj": "root",
        "line": 451,
        "column": 0,
        "endLine": 451,
        "endColumn": 14,
        "path": "main.py",
        "symbol": "function-redefined",
        "message": "function already defined line 310",
        "message-id": "E0102"
    },
    {
        "type": "warning",
        "module": "main",
        "obj": "list_devices",
        "line": 478,
        "column": 8,
        "endLine": 478,
        "endColumn": 15,
        "path": "main.py",
        "symbol": "redefined-outer-name",
        "message": "Redefining name 'manager' from outer scope (line 243)",
        "message-id": "W0621"
    },
    {
        "type": "warning",
        "module": "main",
        "obj": "list_devices",
        "line": 507,
        "column": 11,
        "endLine": 507,
        "endColumn": 20,
        "path": "main.py",
        "symbol": "broad-exception-caught",
        "message": "Catching too general exception Exception",
        "message-id": "W0718"
    },
    {
        "type": "warning",
        "module": "main",
        "obj": "list_devices",
        "line": 472,
        "column": 4,
        "endLine": 472,
        "endColumn": 20,
        "path": "main.py",
        "symbol": "unused-argument",
        "message": "Unused argument 'request'",
        "message-id": "W0613"
    },
    {
        "type": "warning",
        "module": "main",
        "obj": "list_devices",
        "line": 474,
        "column": 4,
        "endLine": 474,
        "endColumn": 16,
        "path": "main.py",
        "symbol": "unused-argument",
        "message": "Unused argument 'api_key'",
        "message-id": "W0613"
    },
    {
        "type": "warning",
        "module": "main",
        "obj": "get_device",
        "line": 520,
        "column": 8,
        "endLine": 520,
        "endColumn": 15,
        "path": "main.py",
        "symbol": "redefined-outer-name",
        "message": "Redefining name 'manager' from outer scope (line 243)",
        "message-id": "W0621"
    },
    {
        "type": "warning",
        "module": "main",
        "obj": "get_device",
        "line": 542,
        "column": 11,
        "endLine": 542,
        "endColumn": 20,
        "path": "main.py",
        "symbol": "broad-exception-caught",
        "message": "Catching too general exception Exception",
        "message-id": "W0718"
    },
    {
        "type": "warning",
        "module": "main",
        "obj": "get_device",
        "line": 514,
        "column": 4,
        "endLine": 514,
        "endColumn": 20,
        "path": "main.py",
        "symbol": "unused-argument",
        "message": "Unused argument 'request'",
        "message-id": "W0613"
    },
    {
        "type": "warning",
        "module": "main",
        "obj": "get_device",
        "line": 516,
        "column": 4,
        "endLine": 516,
        "endColumn": 16,
        "path": "main.py",
        "symbol": "unused-argument",
        "message": "Unused argument 'api_key'",
        "message-id": "W0613"
    },
    {
        "type": "warning",
        "module": "main",
        "obj": "connect_device",
        "line": 557,
        "column": 8,
        "endLine": 557,
        "endColumn": 15,
        "path": "main.py",
        "symbol": "redefined-outer-name",
        "message": "Redefining name 'manager' from outer scope (line 243)",
        "message-id": "W0621"
    },
    {
        "type": "warning",
        "module": "main",
        "obj": "connect_device",
        "line": 588,
        "column": 11,
        "endLine": 588,
        "endColumn": 20,
        "path": "main.py",
        "symbol": "broad-exception-caught",
        "message": "Catching too general exception Exception",
        "message-id": "W0718"
    },
    {
        "type": "refactor",
        "module": "main",
        "obj": "connect_device",
        "line": 563,
        "column": 8,
        "endLine": 586,
        "endColumn": 86,
        "path": "main.py",
        "symbol": "no-else-return",
        "message": "Unnecessary \"else\" after \"return\", remove the \"else\" and de-indent the code inside it",
        "message-id": "R1705"
    },
    {
        "type": "warning",
        "module": "main",
        "obj": "connect_device",
        "line": 552,
        "column": 4,
        "endLine": 552,
        "endColumn": 16,
        "path": "main.py",
        "symbol": "unused-argument",
        "message": "Unused argument 'api_key'",
        "message-id": "W0613"
    },
    {
        "type": "warning",
        "module": "main",
        "obj": "connect_device",
        "line": 560,
        "column": 8,
        "endLine": 560,
        "endColumn": 16,
        "path": "main.py",
        "symbol": "unused-variable",
        "message": "Unused variable 'wireless'",
        "message-id": "W0612"
    },
    {
        "type": "warning",
        "module": "main",
        "obj": "disconnect_device",
        "line": 602,
        "column": 8,
        "endLine": 602,
        "endColumn": 15,
        "path": "main.py",
        "symbol": "redefined-outer-name",
        "message": "Redefining name 'manager' from outer scope (line 243)",
        "message-id": "W0621"
    },
    {
        "type": "warning",
        "module": "main",
        "obj": "disconnect_device",
        "line": 628,
        "column": 11,
        "endLine": 628,
        "endColumn": 20,
        "path": "main.py",
        "symbol": "broad-exception-caught",
        "message": "Catching too general exception Exception",
        "message-id": "W0718"
    },
    {
        "type": "refactor",
        "module": "main",
        "obj": "disconnect_device",
        "line": 607,
        "column": 8,
        "endLine": 626,
        "endColumn": 86,
        "path": "main.py",
        "symbol": "no-else-return",
        "message": "Unnecessary \"else\" after \"return\", remove the \"else\" and de-indent the code inside it",
        "message-id": "R1705"
    },
    {
        "type": "warning",
        "module": "main",
        "obj": "disconnect_device",
        "line": 597,
        "column": 4,
        "endLine": 597,
        "endColumn": 16,
        "path": "main.py",
        "symbol": "unused-argument",
        "message": "Unused argument 'api_key'",
        "message-id": "W0613"
    },
    {
        "type": "warning",
        "module": "main",
        "obj": "click",
        "line": 669,
        "column": 11,
        "endLine": 669,
        "endColumn": 20,
        "path": "main.py",
        "symbol": "broad-exception-caught",
        "message": "Catching too general exception Exception",
        "message-id": "W0718"
    },
    {
        "type": "refactor",
        "module": "main",
        "obj": "click",
        "line": 662,
        "column": 8,
        "endLine": 667,
        "endColumn": 55,
        "path": "main.py",
        "symbol": "no-else-return",
        "message": "Unnecessary \"else\" after \"return\", remove the \"else\" and de-indent the code inside it",
        "message-id": "R1705"
    },
    {
        "type": "warning",
        "module": "main",
        "obj": "click",
        "line": 640,
        "column": 4,
        "endLine": 640,
        "endColumn": 16,
        "path": "main.py",
        "symbol": "unused-argument",
        "message": "Unused argument 'api_key'",
        "message-id": "W0613"
    },
    {
        "type": "refactor",
        "module": "main",
        "obj": "swipe",
        "line": 675,
        "column": 0,
        "endLine": 675,
        "endColumn": 15,
        "path": "main.py",
        "symbol": "too-many-locals",
        "message": "Too many local variables (16/15)",
        "message-id": "R0914"
    },
    {
        "type": "warning",
        "module": "main",
        "obj": "swipe",
        "line": 709,
        "column": 11,
        "endLine": 709,
        "endColumn": 20,
        "path": "main.py",
        "symbol": "broad-exception-caught",
        "message": "Catching too general exception Exception",
        "message-id": "W0718"
    },
    {
        "type": "refactor",
        "module": "main",
        "obj": "swipe",
        "line": 700,
        "column": 8,
        "endLine": 705,
        "endColumn": 61,
        "path": "main.py",
        "symbol": "no-else-return",
        "message": "Unnecessary \"else\" after \"return\", remove the \"else\" and de-indent the code inside it",
        "message-id": "R1705"
    },
    {
        "type": "warning",
        "module": "main",
        "obj": "swipe",
        "line": 679,
        "column": 4,
        "endLine": 679,
        "endColumn": 16,
        "path": "main.py",
        "symbol": "unused-argument",
        "message": "Unused argument 'api_key'",
        "message-id": "W0613"
    },
    {
        "type": "warning",
        "module": "main",
        "obj": "input_text",
        "line": 736,
        "column": 11,
        "endLine": 736,
        "endColumn": 20,
        "path": "main.py",
        "symbol": "broad-exception-caught",
        "message": "Catching too general exception Exception",
        "message-id": "W0718"
    },
    {
        "type": "refactor",
        "module": "main",
        "obj": "input_text",
        "line": 729,
        "column": 8,
        "endLine": 734,
        "endColumn": 61,
        "path": "main.py",
        "symbol": "no-else-return",
        "message": "Unnecessary \"else\" after \"return\", remove the \"else\" and de-indent the code inside it",
        "message-id": "R1705"
    },
    {
        "type": "warning",
        "module": "main",
        "obj": "input_text",
        "line": 719,
        "column": 4,
        "endLine": 719,
        "endColumn": 16,
        "path": "main.py",
        "symbol": "unused-argument",
        "message": "Unused argument 'api_key'",
        "message-id": "W0613"
    },
    {
        "type": "warning",
        "module": "main",
        "obj": "press_key",
        "line": 763,
        "column": 11,
        "endLine": 763,
        "endColumn": 20,
        "path": "main.py",
        "symbol": "broad-exception-caught",
        "message": "Catching too general exception Exception",
        "message-id": "W0718"
    },
    {
        "type": "refactor",
        "module": "main",
        "obj": "press_key",
        "line": 756,
        "column": 8,
        "endLine": 761,
        "endColumn": 61,
        "path": "main.py",
        "symbol": "no-else-return",
        "message": "Unnecessary \"else\" after \"return\", remove the \"else\" and de-indent the code inside it",
        "message-id": "R1705"
    },
    {
        "type": "warning",
        "module": "main",
        "obj": "press_key",
        "line": 746,
        "column": 4,
        "endLine": 746,
        "endColumn": 16,
        "path": "main.py",
        "symbol": "unused-argument",
        "message": "Unused argument 'api_key'",
        "message-id": "W0613"
    },
    {
        "type": "warning",
        "module": "main",
        "obj": "take_screenshot",
        "line": 808,
        "column": 11,
        "endLine": 808,
        "endColumn": 20,
        "path": "main.py",
        "symbol": "broad-exception-caught",
        "message": "Catching too general exception Exception",
        "message-id": "W0718"
    },
    {
        "type": "refactor",
        "module": "main",
        "obj": "take_screenshot",
        "line": 785,
        "column": 8,
        "endLine": 806,
        "endColumn": 55,
        "path": "main.py",
        "symbol": "no-else-return",
        "message": "Unnecessary \"else\" after \"return\", remove the \"else\" and de-indent the code inside it",
        "message-id": "R1705"
    },
    {
        "type": "warning",
        "module": "main",
        "obj": "take_screenshot",
        "line": 773,
        "column": 4,
        "endLine": 773,
        "endColumn": 16,
        "path": "main.py",
        "symbol": "unused-argument",
        "message": "Unused argument 'api_key'",
        "message-id": "W0613"
    },
    {
        "type": "warning",
        "module": "main",
        "obj": "list_scripts",
        "line": 828,
        "column": 11,
        "endLine": 828,
        "endColumn": 20,
        "path": "main.py",
        "symbol": "broad-exception-caught",
        "message": "Catching too general exception Exception",
        "message-id": "W0718"
    },
    {
        "type": "warning",
        "module": "main",
        "obj": "list_scripts",
        "line": 817,
        "column": 4,
        "endLine": 817,
        "endColumn": 20,
        "path": "main.py",
        "symbol": "unused-argument",
        "message": "Unused argument 'request'",
        "message-id": "W0613"
    },
    {
        "type": "warning",
        "module": "main",
        "obj": "list_scripts",
        "line": 819,
        "column": 4,
        "endLine": 819,
        "endColumn": 16,
        "path": "main.py",
        "symbol": "unused-argument",
        "message": "Unused argument 'api_key'",
        "message-id": "W0613"
    },
    {
        "type": "warning",
        "module": "main",
        "obj": "get_script",
        "line": 847,
        "column": 11,
        "endLine": 847,
        "endColumn": 20,
        "path": "main.py",
        "symbol": "broad-exception-caught",
        "message": "Catching too general exception Exception",
        "message-id": "W0718"
    },
    {
        "type": "refactor",
        "module": "main",
        "obj": "get_script",
        "line": 843,
        "column": 8,
        "endLine": 846,
        "endColumn": 72,
        "path": "main.py",
        "symbol": "no-else-return",
        "message": "Unnecessary \"else\" after \"return\", remove the \"else\" and de-indent the code inside it",
        "message-id": "R1705"
    },
    {
        "type": "warning",
        "module": "main",
        "obj": "get_script",
        "line": 835,
        "column": 4,
        "endLine": 835,
        "endColumn": 20,
        "path": "main.py",
        "symbol": "unused-argument",
        "message": "Unused argument 'request'",
        "message-id": "W0613"
    },
    {
        "type": "warning",
        "module": "main",
        "obj": "get_script",
        "line": 837,
        "column": 4,
        "endLine": 837,
        "endColumn": 16,
        "path": "main.py",
        "symbol": "unused-argument",
        "message": "Unused argument 'api_key'",
        "message-id": "W0613"
    },
    {
        "type": "warning",
        "module": "main",
        "obj": "create_script",
        "line": 877,
        "column": 11,
        "endLine": 877,
        "endColumn": 20,
        "path": "main.py",
        "symbol": "broad-exception-caught",
        "message": "Catching too general exception Exception",
        "message-id": "W0718"
    },
    {
        "type": "warning",
        "module": "main",
        "obj": "create_script",
        "line": 854,
        "column": 4,
        "endLine": 854,
        "endColumn": 20,
        "path": "main.py",
        "symbol": "unused-argument",
        "message": "Unused argument 'request'",
        "message-id": "W0613"
    },
    {
        "type": "warning",
        "module": "main",
        "obj": "create_script",
        "line": 856,
        "column": 4,
        "endLine": 856,
        "endColumn": 16,
        "path": "main.py",
        "symbol": "unused-argument",
        "message": "Unused argument 'api_key'",
        "message-id": "W0613"
    },
    {
        "type": "warning",
        "module": "main",
        "obj": "update_script",
        "line": 911,
        "column": 11,
        "endLine": 911,
        "endColumn": 20,
        "path": "main.py",
        "symbol": "broad-exception-caught",
        "message": "Catching too general exception Exception",
        "message-id": "W0718"
    },
    {
        "type": "warning",
        "module": "main",
        "obj": "update_script",
        "line": 884,
        "column": 4,
        "endLine": 884,
        "endColumn": 20,
        "path": "main.py",
        "symbol": "unused-argument",
        "message": "Unused argument 'request'",
        "message-id": "W0613"
    },
    {
        "type": "warning",
        "module": "main",
        "obj": "update_script",
        "line": 887,
        "column": 4,
        "endLine": 887,
        "endColumn": 16,
        "path": "main.py",
        "symbol": "unused-argument",
        "message": "Unused argument 'api_key'",
        "message-id": "W0613"
    },
    {
        "type": "warning",
        "module": "main",
        "obj": "delete_script",
        "line": 930,
        "column": 11,
        "endLine": 930,
        "endColumn": 20,
        "path": "main.py",
        "symbol": "broad-exception-caught",
        "message": "Catching too general exception Exception",
        "message-id": "W0718"
    },
    {
        "type": "refactor",
        "module": "main",
        "obj": "delete_script",
        "line": 926,
        "column": 8,
        "endLine": 929,
        "endColumn": 72,
        "path": "main.py",
        "symbol": "no-else-return",
        "message": "Unnecessary \"else\" after \"return\", remove the \"else\" and de-indent the code inside it",
        "message-id": "R1705"
    },
    {
        "type": "warning",
        "module": "main",
        "obj": "delete_script",
        "line": 918,
        "column": 4,
        "endLine": 918,
        "endColumn": 20,
        "path": "main.py",
        "symbol": "unused-argument",
        "message": "Unused argument 'request'",
        "message-id": "W0613"
    },
    {
        "type": "warning",
        "module": "main",
        "obj": "delete_script",
        "line": 920,
        "column": 4,
        "endLine": 920,
        "endColumn": 16,
        "path": "main.py",
        "symbol": "unused-argument",
        "message": "Unused argument 'api_key'",
        "message-id": "W0613"
    },
    {
        "type": "warning",
        "module": "main",
        "obj": "execute_script",
        "line": 977,
        "column": 11,
        "endLine": 977,
        "endColumn": 20,
        "path": "main.py",
        "symbol": "broad-exception-caught",
        "message": "Catching too general exception Exception",
        "message-id": "W0718"
    },
    {
        "type": "warning",
        "module": "main",
        "obj": "execute_script",
        "line": 940,
        "column": 4,
        "endLine": 940,
        "endColumn": 16,
        "path": "main.py",
        "symbol": "unused-argument",
        "message": "Unused argument 'api_key'",
        "message-id": "W0613"
    },
    {
        "type": "warning",
        "module": "main",
        "obj": "start_recording",
        "line": 1007,
        "column": 11,
        "endLine": 1007,
        "endColumn": 20,
        "path": "main.py",
        "symbol": "broad-exception-caught",
        "message": "Catching too general exception Exception",
        "message-id": "W0718"
    },
    {
        "type": "refactor",
        "module": "main",
        "obj": "start_recording",
        "line": 1001,
        "column": 8,
        "endLine": 1005,
        "endColumn": 61,
        "path": "main.py",
        "symbol": "no-else-return",
        "message": "Unnecessary \"else\" after \"return\", remove the \"else\" and de-indent the code inside it",
        "message-id": "R1705"
    },
    {
        "type": "warning",
        "module": "main",
        "obj": "start_recording",
        "line": 986,
        "column": 4,
        "endLine": 986,
        "endColumn": 20,
        "path": "main.py",
        "symbol": "unused-argument",
        "message": "Unused argument 'request'",
        "message-id": "W0613"
    },
    {
        "type": "warning",
        "module": "main",
        "obj": "start_recording",
        "line": 988,
        "column": 4,
        "endLine": 988,
        "endColumn": 16,
        "path": "main.py",
        "symbol": "unused-argument",
        "message": "Unused argument 'api_key'",
        "message-id": "W0613"
    },
    {
        "type": "warning",
        "module": "main",
        "obj": "stop_recording",
        "line": 1033,
        "column": 11,
        "endLine": 1033,
        "endColumn": 20,
        "path": "main.py",
        "symbol": "broad-exception-caught",
        "message": "Catching too general exception Exception",
        "message-id": "W0718"
    },
    {
        "type": "warning",
        "module": "main",
        "obj": "stop_recording",
        "line": 1014,
        "column": 4,
        "endLine": 1014,
        "endColumn": 20,
        "path": "main.py",
        "symbol": "unused-argument",
        "message": "Unused argument 'request'",
        "message-id": "W0613"
    },
    {
        "type": "warning",
        "module": "main",
        "obj": "stop_recording",
        "line": 1016,
        "column": 4,
        "endLine": 1016,
        "endColumn": 16,
        "path": "main.py",
        "symbol": "unused-argument",
        "message": "Unused argument 'api_key'",
        "message-id": "W0613"
    },
    {
        "type": "warning",
        "module": "main",
        "obj": "get_record_status",
        "line": 1058,
        "column": 11,
        "endLine": 1058,
        "endColumn": 20,
        "path": "main.py",
        "symbol": "broad-exception-caught",
        "message": "Catching too general exception Exception",
        "message-id": "W0718"
    },
    {
        "type": "warning",
        "module": "main",
        "obj": "get_record_status",
        "line": 1040,
        "column": 4,
        "endLine": 1040,
        "endColumn": 20,
        "path": "main.py",
        "symbol": "unused-argument",
        "message": "Unused argument 'request'",
        "message-id": "W0613"
    },
    {
        "type": "warning",
        "module": "main",
        "obj": "get_record_status",
        "line": 1042,
        "column": 4,
        "endLine": 1042,
        "endColumn": 16,
        "path": "main.py",
        "symbol": "unused-argument",
        "message": "Unused argument 'api_key'",
        "message-id": "W0613"
    },
    {
        "type": "warning",
        "module": "main",
        "obj": "record_action",
        "line": 1089,
        "column": 11,
        "endLine": 1089,
        "endColumn": 20,
        "path": "main.py",
        "symbol": "broad-exception-caught",
        "message": "Catching too general exception Exception",
        "message-id": "W0718"
    },
    {
        "type": "refactor",
        "module": "main",
        "obj": "record_action",
        "line": 1084,
        "column": 8,
        "endLine": 1087,
        "endColumn": 61,
        "path": "main.py",
        "symbol": "no-else-return",
        "message": "Unnecessary \"else\" after \"return\", remove the \"else\" and de-indent the code inside it",
        "message-id": "R1705"
    },
    {
        "type": "warning",
        "module": "main",
        "obj": "record_action",
        "line": 1065,
        "column": 4,
        "endLine": 1065,
        "endColumn": 20,
        "path": "main.py",
        "symbol": "unused-argument",
        "message": "Unused argument 'request'",
        "message-id": "W0613"
    },
    {
        "type": "warning",
        "module": "main",
        "obj": "record_action",
        "line": 1068,
        "column": 4,
        "endLine": 1068,
        "endColumn": 16,
        "path": "main.py",
        "symbol": "unused-argument",
        "message": "Unused argument 'api_key'",
        "message-id": "W0613"
    },
    {
        "type": "refactor",
        "module": "main",
        "obj": "get_logs",
        "line": 1097,
        "column": 0,
        "endLine": 1097,
        "endColumn": 18,
        "path": "main.py",
        "symbol": "too-many-arguments",
        "message": "Too many arguments (6/5)",
        "message-id": "R0913"
    },
    {
        "type": "warning",
        "module": "main",
        "obj": "get_logs",
        "line": 1113,
        "column": 11,
        "endLine": 1113,
        "endColumn": 20,
        "path": "main.py",
        "symbol": "broad-exception-caught",
        "message": "Catching too general exception Exception",
        "message-id": "W0718"
    },
    {
        "type": "warning",
        "module": "main",
        "obj": "get_logs",
        "line": 1098,
        "column": 4,
        "endLine": 1098,
        "endColumn": 20,
        "path": "main.py",
        "symbol": "unused-argument",
        "message": "Unused argument 'request'",
        "message-id": "W0613"
    },
    {
        "type": "warning",
        "module": "main",
        "obj": "get_logs",
        "line": 1103,
        "column": 4,
        "endLine": 1103,
        "endColumn": 16,
        "path": "main.py",
        "symbol": "unused-argument",
        "message": "Unused argument 'api_key'",
        "message-id": "W0613"
    },
    {
        "type": "warning",
        "module": "main",
        "obj": "",
        "line": 1124,
        "column": 15,
        "endLine": 1124,
        "endColumn": 38,
        "path": "main.py",
        "symbol": "invalid-envvar-default",
        "message": "os.getenv default type is builtins.int. Expected str or None.",
        "message-id": "W1508"
    },
    {
        "type": "warning",
        "module": "main",
        "obj": "",
        "line": 1126,
        "column": 10,
        "endLine": 1126,
        "endColumn": 49,
        "path": "main.py",
        "symbol": "f-string-without-interpolation",
        "message": "Using an f-string that does not have any interpolated variables",
        "message-id": "W1309"
    },
    {
        "type": "warning",
        "module": "main",
        "obj": "",
        "line": 9,
        "column": 0,
        "endLine": 9,
        "endColumn": 13,
        "path": "main.py",
        "symbol": "unused-import",
        "message": "Unused import base64",
        "message-id": "W0611"
    },
    {
        "type": "warning",
        "module": "main",
        "obj": "",
        "line": 10,
        "column": 0,
        "endLine": 10,
        "endColumn": 16,
        "path": "main.py",
        "symbol": "unused-import",
        "message": "Unused import traceback",
        "message-id": "W0611"
    },
    {
        "type": "warning",
        "module": "main",
        "obj": "",
        "line": 11,
        "column": 0,
        "endLine": 11,
        "endColumn": 14,
        "path": "main.py",
        "symbol": "unused-import",
        "message": "Unused import asyncio",
        "message-id": "W0611"
    },
    {
        "type": "warning",
        "module": "main",
        "obj": "",
        "line": 20,
        "column": 0,
        "endLine": 20,
        "endColumn": 109,
        "path": "main.py",
        "symbol": "unused-import",
        "message": "Unused Response imported from fastapi",
        "message-id": "W0611"
    },
    {
        "type": "warning",
        "module": "main",
        "obj": "",
        "line": 32,
        "column": 0,
        "endLine": 32,
        "endColumn": 78,
        "path": "main.py",
        "symbol": "unused-import",
        "message": "Unused DeviceManager imported from src.device_manager",
        "message-id": "W0611"
    },
    {
        "type": "warning",
        "module": "main",
        "obj": "",
        "line": 33,
        "column": 0,
        "endLine": 33,
        "endColumn": 59,
        "path": "main.py",
        "symbol": "unused-import",
        "message": "Unused ADBClient imported from src.adb_client",
        "message-id": "W0611"
    },
    {
        "type": "warning",
        "module": "main",
        "obj": "",
        "line": 33,
        "column": 0,
        "endLine": 33,
        "endColumn": 59,
        "path": "main.py",
        "symbol": "unused-import",
        "message": "Unused Point imported from src.adb_client",
        "message-id": "W0611"
    },
    {
        "type": "warning",
        "module": "main",
        "obj": "",
        "line": 34,
        "column": 0,
        "endLine": 34,
        "endColumn": 62,
        "path": "main.py",
        "symbol": "unused-import",
        "message": "Unused ScreenController imported from src.screen",
        "message-id": "W0611"
    },
    {
        "type": "warning",
        "module": "main",
        "obj": "",
        "line": 35,
        "column": 0,
        "endLine": 35,
        "endColumn": 73,
        "path": "main.py",
        "symbol": "unused-import",
        "message": "Unused ScriptRunner imported from src.script_runner",
        "message-id": "W0611"
    },
    {
        "type": "warning",
        "module": "main",
        "obj": "",
        "line": 35,
        "column": 0,
        "endLine": 35,
        "endColumn": 73,
        "path": "main.py",
        "symbol": "unused-import",
        "message": "Unused ActionType imported from src.script_runner",
        "message-id": "W0611"
    }
]
